{"city": "\u5f70\u5316\u7e23", "town": "\u57e4\u982d\u9109", "zipcode": "523", "data": [{"id": "010088", "name": "\u5168\u5bb6\u57e4\u982d\u5927\u8c50\u5e97", "address": "\u5f70\u5316\u7e23\u57e4\u982d\u9109\u6597\u82d1\u6771\u8def\uff12\u4e4b\uff15\u865f", "zipcode": "523", "city": "\u5f70\u5316\u7e23", "town": "\u57e4\u982d\u9109", "data": [{"name": "\u9ebb\u6cb9\u96de\u98ef\u7cf0", "qty": 1, "scate": "\u98ef\u7cf0\uff14\u5ea6\uff23", "cate": "\u98ef\u7cf0\u624b\u5377"}, {"name": "\u5927\u53e3\u849c\u5473\u9999\u8178\u71d2\u8089\u96d9\u62fc\u98ef\u7cf0", "qty": 1, "scate": "\u98ef\u7cf0\uff14\u5ea6\uff23", "cate": "\u98ef\u7cf0\u624b\u5377"}, {"name": "\u5fb7\u5f0f\u9178\u83dc\u71fb\u8178\u98ef\u5377", "qty": 1, "scate": "\uff14\u2103\u58fd\u53f8\u624b\u5377", "cate": "\u98ef\u7cf0\u624b\u5377"}, {"name": "\u9ebb\u6cb9\u9e7d\u7099\u70e4\u8c6c\u8089\u98ef\u5377", "qty": 1, "scate": "\uff14\u2103\u58fd\u53f8\u624b\u5377", "cate": "\u98ef\u7cf0\u624b\u5377"}, {"name": "\u4e00\u914d\u5169\u7c92\u98ef\u7cf0(\u9baa\u9b5a.\u7126\u7cd6\u9bad\u9b5a)", "qty": 1, "scate": "\u98ef\u7cf0\u4e00\u914d", "cate": "\u98ef\u7cf0\u624b\u5377"}, {"name": "\u661f-\u6975\u4e0a\u7099\u70e4\u89aa\u5b50\u4e3c", "qty": 1, "scate": "\u65e5\u5f0f\u4e3b\u98df\u4e00\u914d", "cate": "\u98ef\u985e\u4e3b\u98df"}, {"name": "\u661f-\u5065\u8eabG\u8089\u9910\u76d2", "qty": 1, "scate": "\u4fbf\u7576\uff14\u2103", "cate": "\u98ef\u985e\u4e3b\u98df"}, {"name": "\u661f-\u5609\u7fa9\u5289\u91cc\u9577\u96de\u8089\u98ef", "qty": 1, "scate": "\u4fbf\u7576\uff14\u2103", "cate": "\u98ef\u985e\u4e3b\u98df"}, {"name": "\u6d77\u9678\u96d9\u62fc\u8089\u8089\u9910\u76d2", "qty": 1, "scate": "\u4fbf\u7576\uff14\u2103", "cate": "\u98ef\u985e\u4e3b\u98df"}, {"name": "\u9999\u8178\u817f\u6392\u96d9\u62fc\u4fbf\u7576", "qty": 1, "scate": "\u4fbf\u7576\uff14\u2103", "cate": "\u98ef\u985e\u4e3b\u98df"}, {"name": "\u86e4\u870a\u4e94\u76ee\u4e2d\u83ef\u71f4\u9eb5", "qty": 1, "scate": "\u71b1\u98df\u9eb5", "cate": "\u9eb5\u985e\u4e3b\u98df"}, {"name": "\u9752\u91ac\u86e4\u870a\u7fa9\u5927\u5229\u9eb5", "qty": 1, "scate": "\u7fa9\u5927\u5229\u9eb5", "cate": "\u9eb5\u985e\u4e3b\u98df"}, {"name": "\u62db\u724c\u9ad8\u9e97\u83dc\u934b\u8cbc", "qty": 1, "scate": "\u9eb5\u9ede", "cate": "\u6e6f\u54c1\u5c0f\u5403"}, {"name": "\u6d77\u85fb\u91ce\u83dc\u6c99\u62c9", "qty": 1, "scate": "\u6c99\u62c9", "cate": "\u4e09\u660e\u6cbb\u6c99\u62c9"}, {"name": "\u6b50\u5f0f\u7530\u5712\u6c99\u62c9", "qty": 1, "scate": "\u6c99\u62c9", "cate": "\u4e09\u660e\u6cbb\u6c99\u62c9"}, {"name": "\u7d93\u5178\u706b\u817f\u7389\u7c73\u86cb\u4e09\u660e\u6cbb", "qty": 1, "scate": "\u4e09\u660e\u6cbb\uff14\u5ea6\uff23", "cate": "\u4e09\u660e\u6cbb\u6c99\u62c9"}, {"name": "\u7da0\u8089\u54c8\u5bc6\u74dc\uff08\u622a\u5207-\u76d2\uff09", "qty": 1, "scate": "\u622a\u5207\u6c34\u679c", "cate": "\u852c\u679c"}, {"name": "\u661f-\u4e00\u914d\u9e7d\u9eb4\u8525\u82b1\u9eb5\u5305", "qty": 1, "scate": "\u751c\u9eb5\u5305", "cate": "\u9eb5\u5305\u751c\u9ede"}, {"name": "\u4e8c\u914d\u751f\u699b\u679c\u6fc3\u53ef\u53ef\u6eff\u9921\u9eb5\u5305", "qty": 1, "scate": "\u9eb5\u5305\u4e8c\u914d", "cate": "\u9eb5\u5305\u751c\u9ede"}, {"name": "\u4e8c\u914d\u751f\u9752\u68ee\u860b\u679c\u6eff\u9921\u9eb5\u5305", "qty": 1, "scate": "\u9eb5\u5305\u4e8c\u914d", "cate": "\u9eb5\u5305\u751c\u9ede"}, {"name": "\u4e8c\u914d\u8d77\u9165\u8089\u9b06\u9eb5\u5305", "qty": 1, "scate": "\u9eb5\u5305\u4e8c\u914d", "cate": "\u9eb5\u5305\u751c\u9ede"}, {"name": "\u767d\u862d\u5730\u8461\u8404\u9905\u4e7e\u593e\u5fc3", "qty": 1, "scate": "\u624b\u5de5\u751c\u9ede", "cate": "\u9eb5\u5305\u751c\u9ede"}, {"name": "\u53cd\u70e4\u7126\u7cd6\u5e03\u4e01\u86cb\u7cd5", "qty": 1, "scate": "\u624b\u5de5\u751c\u9ede", "cate": "\u9eb5\u5305\u751c\u9ede"}, {"name": "\u4e8c\u914d\u85cd\u8393\u593e\u5fc3\u571f\u53f8", "qty": 1, "scate": "\u5410\u53f8\u86cb\u7cd5\u4e8c\u914d", "cate": "\u86cb\u7cd5\u5410\u53f8"}, {"name": "\u661f-\u4e8c\u914d\u82b1\u751f\u593e\u5fc3\u571f\u53f8", "qty": 2, "scate": "\u5410\u53f8\u86cb\u7cd5\u4e8c\u914d", "cate": "\u86cb\u7cd5\u5410\u53f8"}, {"name": "\u4e8c\u914d\u967d\u5149\u8461\u8404\u571f\u53f8", "qty": 1, "scate": "\u5410\u53f8\u86cb\u7cd5\u4e8c\u914d", "cate": "\u86cb\u7cd5\u5410\u53f8"}]}], "updatetime": 1762952796}