{"city": "\u6f8e\u6e56\u7e23", "town": "\u767d\u6c99\u9109", "zipcode": "884", "data": [{"id": "021598", "name": "\u5168\u5bb6\u6f8e\u6e56\u8de8\u6d77\u5e97", "address": "\u6f8e\u6e56\u7e23\u767d\u6c99\u9109\u901a\u6881\u6751\u901a\u6881\uff11\uff19\uff15\u865f\u4e00\u6a13", "zipcode": "884", "city": "\u6f8e\u6e56\u7e23", "town": "\u767d\u6c99\u9109", "data": [{"name": "\u68a8\u5c71\u7518\u9732\u68a8(\u622a\u5207-\u888b)", "qty": 1, "scate": "\u622a\u5207\u6c34\u679c", "cate": "\u852c\u679c"}]}, {"id": "022635", "name": "\u5168\u5bb6\u6f8e\u6e56\u9f8d\u5fb7\u5e97", "address": "\u6f8e\u6e56\u7e23\u767d\u6c99\u9109\u5927\u8d64\u5d01\uff13\uff11\u865f", "zipcode": "884", "city": "\u6f8e\u6e56\u7e23", "town": "\u767d\u6c99\u9109", "data": [{"name": "\u512a\u8cea\u6c60\u4e0a\u98ef", "qty": 1, "scate": "\u5176\u4ed6\u98ef\u985e\u4e00\u914d", "cate": "\u98ef\u985e\u4e3b\u98df"}, {"name": "\u68a8\u5c71\u7518\u9732\u68a8(\u622a\u5207-\u888b)", "qty": 1, "scate": "\u622a\u5207\u6c34\u679c", "cate": "\u852c\u679c"}, {"name": "\u4e00\u914d\u5976\u9999\u7dbf\u96f2\u5c0f\u571f\u53f8", "qty": 1, "scate": "\u5c0f\u5410\u53f8\u9910\u5305", "cate": "\u86cb\u7cd5\u5410\u53f8"}]}], "updatetime": 1763035809}