{"city": "\u5c4f\u6771\u7e23", "town": "\u7409\u7403\u9109", "zipcode": "929", "data": [{"id": "017329", "name": "\u5168\u5bb6\u7409\u7403\u767d\u6c99\u5e97", "address": "\u5c4f\u6771\u7e23\u7409\u7403\u9109\u6c11\u751f\u8def\uff12\u4e4b\uff16\u865f", "zipcode": "929", "city": "\u5c4f\u6771\u7e23", "town": "\u7409\u7403\u9109", "data": [{"name": "\u9999\u83c7\u96de\u7ca5", "qty": 1, "scate": "\u7ca5\u54c1\u4e00\u914d", "cate": "\u98ef\u985e\u4e3b\u98df"}, {"name": "\u53f0\u5f0f\u7d9c\u5408\u751c\u4e0d\u8fa3", "qty": 1, "scate": "\u7279\u8272\u5c0f\u5403", "cate": "\u6e6f\u54c1\u5c0f\u5403"}, {"name": "\u97d3\u5f0f\u90e8\u968a\u934b", "qty": 1, "scate": "\u6e6f\u54c1", "cate": "\u6e6f\u54c1\u5c0f\u5403"}, {"name": "\u65e5\u5f0f\u58fd\u559c\u71d2", "qty": 1, "scate": "\u6e6f\u54c1", "cate": "\u6e6f\u54c1\u5c0f\u5403"}, {"name": "\u5b8c\u719f\u7d05\u9f8d\u679c(\u8d85\u503c\u76d2)", "qty": 1, "scate": "\u622a\u5207\u6c34\u679c", "cate": "\u852c\u679c"}, {"name": "\u5c65\u6b77\u73cd\u73e0\u82ad\u6a02\uff08\u622a\u5207\uff0d\u888b\uff09", "qty": 2, "scate": "\u622a\u5207\u6c34\u679c", "cate": "\u852c\u679c"}]}], "updatetime": 1762938345}