{"city": "\u82d7\u6817\u7e23", "town": "\u7af9\u5357\u93ae", "zipcode": "350", "data": [{"id": "260172", "name": "AP6B", "address": "\u82d7\u6817\u7e23\u7af9\u5357\u93ae\u79d1\u5c08\u4e03\u8def1\u865f", "city": "\u82d7\u6817\u7e23", "town": "\u7af9\u5357\u93ae", "data": []}, {"id": "233712", "name": "AP\u516d", "address": "\u82d7\u6817\u7e23\u7af9\u5357\u93ae\u5927\u57d4\u91cc\u79d1\u5c08\u4e00\u8def1\u865f", "city": "\u82d7\u6817\u7e23", "town": "\u7af9\u5357\u93ae", "data": []}, {"id": "208750", "name": "\u4e8e\u7fa9", "address": "\u82d7\u6817\u7e23\u7af9\u5357\u93ae\u516c\u7fa9\u8def1098\u865f", "city": "\u82d7\u6817\u7e23", "town": "\u7af9\u5357\u93ae", "data": []}, {"id": "276281", "name": "\u5929\u6587", "address": "\u82d7\u6817\u7e23\u7af9\u5357\u93ae\u5929\u6587\u8def176\u865f", "city": "\u82d7\u6817\u7e23", "town": "\u7af9\u5357\u93ae", "data": []}, {"id": "239514", "name": "\u4edf\u7fd4", "address": "\u82d7\u6817\u7e23\u7af9\u5357\u93ae\u9f8d\u5c71\u8def\u4e8c\u6bb5275\u865f", "city": "\u82d7\u6817\u7e23", "town": "\u7af9\u5357\u93ae", "data": []}, {"id": "111854", "name": "\u5e03\u6d1b\u74e6", "address": "\u82d7\u6817\u7e23\u7af9\u5357\u93ae\u79d1\u6771\u4e09\u8def12\u865f", "city": "\u82d7\u6817\u7e23", "town": "\u7af9\u5357\u93ae", "data": []}, {"id": "120537", "name": "\u5f18\u904b", "address": "\u82d7\u6817\u7e23\u7af9\u5357\u93ae\u5b88\u6cd5\u88573-2\u865f3-3\u865f3-5\u865f1\u6a13", "city": "\u82d7\u6817\u7e23", "town": "\u7af9\u5357\u93ae", "data": []}, {"id": "281526", "name": "\u5149\u5357", "address": "\u82d7\u6817\u7e23\u7af9\u5357\u93ae\u7167\u5357\u91cc\u5149\u5fa9\u8def342\u865f", "city": "\u82d7\u6817\u7e23", "town": "\u7af9\u5357\u93ae", "data": []}, {"id": "181679", "name": "\u5733\u71df", "address": "\u82d7\u6817\u7e23\u7af9\u5357\u93ae\u4e2d\u6b63\u8def114\u865f1\u6a13", "city": "\u82d7\u6817\u7e23", "town": "\u7af9\u5357\u93ae", "data": []}, {"id": "116169", "name": "\u7af9\u5357\u548c\u8208", "address": "\u82d7\u6817\u7e23\u7af9\u5357\u93ae\u5927\u57d4\u91cc\u548c\u8208\u8def191-1\u865f", "city": "\u82d7\u6817\u7e23", "town": "\u7af9\u5357\u93ae", "data": []}, {"id": "249980", "name": "\u7af9\u5357\u5efa\u570b", "address": "\u82d7\u6817\u7e23\u7af9\u5357\u93ae\u9f8d\u9cf3\u91cc\u9f8d\u5c71\u8def\u4e00\u6bb5162\u865f1\u6a13", "city": "\u82d7\u6817\u7e23", "town": "\u7af9\u5357\u93ae", "data": []}, {"id": "233848", "name": "\u7af9\u570d\u4ed4", "address": "\u82d7\u6817\u7e23\u7af9\u5357\u93ae\u5fa9\u8208\u8def380\u865f", "city": "\u82d7\u6817\u7e23", "town": "\u7af9\u5357\u93ae", "data": []}, {"id": "208864", "name": "\u6c85\u4e1e", "address": "\u82d7\u6817\u7e23\u7af9\u5357\u93ae\u516c\u7fa9\u91cc\u53cb\u7fa9\u8def67\u865f", "city": "\u82d7\u6817\u7e23", "town": "\u7af9\u5357\u93ae", "data": []}, {"id": "230414", "name": "\u5ef6\u5e73", "address": "\u82d7\u6817\u7e23\u7af9\u5357\u93ae\u7167\u5357\u91cc15\u9130\u5ef6\u5e73\u8def63\u5df71\u865f", "city": "\u82d7\u6817\u7e23", "town": "\u7af9\u5357\u93ae", "data": []}, {"id": "166315", "name": "\u79d1\u4e03", "address": "\u82d7\u6817\u7e23\u7af9\u5357\u93ae\u79d1\u5c08\u4e03\u8def396\u865f1\u6a13", "city": "\u82d7\u6817\u7e23", "town": "\u7af9\u5357\u93ae", "data": []}, {"id": "279833", "name": "\u79d1\u4e94", "address": "\u82d7\u6817\u7e23\u7af9\u5357\u93ae\u5927\u57d4\u91cc\u5927\u57d4\u4e94\u885767\u865f", "city": "\u82d7\u6817\u7e23", "town": "\u7af9\u5357\u93ae", "data": []}, {"id": "233608", "name": "\u79d1\u91d1", "address": "\u82d7\u6817\u7e23\u7af9\u5357\u93ae\u79d1\u5c08\u516d\u8def275\u865f", "city": "\u82d7\u6817\u7e23", "town": "\u7af9\u5357\u93ae", "data": []}, {"id": "183918", "name": "\u79d1\u5357", "address": "\u82d7\u6817\u7e23\u7af9\u5357\u93ae\u5927\u57d4\u91cc1\u9130\u79d1\u5b78\u8def243\u865f", "city": "\u82d7\u6817\u7e23", "town": "\u7af9\u5357\u93ae", "data": []}, {"id": "184368", "name": "\u79d1\u661f", "address": "\u82d7\u6817\u7e23\u7af9\u5357\u93ae\u79d1\u5c08\u4e03\u8def393\u865f", "city": "\u82d7\u6817\u7e23", "town": "\u7af9\u5357\u93ae", "data": []}, {"id": "991296", "name": "\u5c55\u5b8f", "address": "\u82d7\u6817\u7e23\u7af9\u5357\u93ae\u4e2d\u83ef\u8def169\u865f171\u865f1\u6a13", "city": "\u82d7\u6817\u7e23", "town": "\u7af9\u5357\u93ae", "data": []}, {"id": "207067", "name": "\u6d77\u53e3", "address": "\u82d7\u6817\u7e23\u7af9\u5357\u93ae\u660e\u52dd\u8def491-1\u865f", "city": "\u82d7\u6817\u7e23", "town": "\u7af9\u5357\u93ae", "data": []}, {"id": "235475", "name": "\u6d77\u5fc3", "address": "\u82d7\u6817\u7e23\u7af9\u5357\u93ae\u958b\u5143\u8def549\u865f", "city": "\u82d7\u6817\u7e23", "town": "\u7af9\u5357\u93ae", "data": []}, {"id": "254203", "name": "\u6d77\u798f", "address": "\u82d7\u6817\u7e23\u7af9\u5357\u93ae\u660e\u52dd\u8def318\u865f", "city": "\u82d7\u6817\u7e23", "town": "\u7af9\u5357\u93ae", "data": []}, {"id": "215666", "name": "\u771f\u958b", "address": "\u82d7\u6817\u7e23\u7af9\u5357\u93ae\u5927\u539d\u91cc\u958b\u5143\u8def412\u865f1\u6a13", "city": "\u82d7\u6817\u7e23", "town": "\u7af9\u5357\u93ae", "data": []}, {"id": "963187", "name": "\u665f\u4e7e", "address": "\u82d7\u6817\u7e23\u7af9\u5357\u93ae\u4ec1\u611b\u8def902\u865f", "city": "\u82d7\u6817\u7e23", "town": "\u7af9\u5357\u93ae", "data": []}, {"id": "137557", "name": "\u570b\u8c6a", "address": "\u82d7\u6817\u7e23\u7af9\u5357\u93ae\u5ef6\u5e73\u8def170\u865f", "city": "\u82d7\u6817\u7e23", "town": "\u7af9\u5357\u93ae", "data": []}, {"id": "175076", "name": "\u7d71\u5bf6", "address": "\u82d7\u6817\u7e23\u7af9\u5357\u93ae\u79d1\u4e2d\u8def12\u865fB2", "city": "\u82d7\u6817\u7e23", "town": "\u7af9\u5357\u93ae", "data": []}, {"id": "260116", "name": "\u958b\u946b", "address": "\u82d7\u6817\u7e23\u7af9\u5357\u93ae\u548c\u4ec1\u885723\u5df710\u865f", "city": "\u82d7\u6817\u7e23", "town": "\u7af9\u5357\u93ae", "data": []}, {"id": "256782", "name": "\u7167\u5357", "address": "\u82d7\u6817\u7e23\u7af9\u5357\u93ae\u4f73\u8208\u91cc\u81f3\u5584\u88572\u865f", "city": "\u82d7\u6817\u7e23", "town": "\u7af9\u5357\u93ae", "data": []}, {"id": "188142", "name": "\u7fa4\u5275", "address": "\u82d7\u6817\u7e23\u7af9\u5357\u93ae\u9802\u57d4\u91cc\u79d1\u5b78\u8def160\u865f1\u6a13", "city": "\u82d7\u6817\u7e23", "town": "\u7af9\u5357\u93ae", "data": []}, {"id": "256047", "name": "\u9054\u6771", "address": "\u82d7\u6817\u7e23\u7af9\u5357\u93ae\u83ef\u6771\u885783\u865f", "city": "\u82d7\u6817\u7e23", "town": "\u7af9\u5357\u93ae", "data": []}, {"id": "263931", "name": "\u5ee3\u6c85", "address": "\u82d7\u6817\u7e23\u7af9\u5357\u93ae\u516c\u7fa9\u91cc\u516c\u7fa9\u8def1683\u865f1685\u865f1\u6a13", "city": "\u82d7\u6817\u7e23", "town": "\u7af9\u5357\u93ae", "data": []}, {"id": "882080", "name": "\u6176\u7af9", "address": "\u82d7\u6817\u7e23\u7af9\u5357\u93ae\u6c11\u65cf\u885782\u865f\u6c11\u6b0a\u8def47\u865f", "city": "\u82d7\u6817\u7e23", "town": "\u7af9\u5357\u93ae", "data": []}, {"id": "258179", "name": "\u9f8d\u4f73", "address": "\u82d7\u6817\u7e23\u7af9\u5357\u93ae\u9f8d\u5c71\u8def\u4e09\u6bb5152\u865f1\u6a13", "city": "\u82d7\u6817\u7e23", "town": "\u7af9\u5357\u93ae", "data": []}, {"id": "263942", "name": "\u9f8d\u6607", "address": "\u82d7\u6817\u7e23\u7af9\u5357\u93ae\u9f8d\u5c71\u8def\u4e8c\u6bb5120\u865f", "city": "\u82d7\u6817\u7e23", "town": "\u7af9\u5357\u93ae", "data": []}, {"id": "121080", "name": "\u9f8d\u5bb8", "address": "\u82d7\u6817\u7e23\u7af9\u5357\u93ae\u71df\u76e4\u91cc\u535a\u611b\u8857367\u865f1\u6a13", "city": "\u82d7\u6817\u7e23", "town": "\u7af9\u5357\u93ae", "data": []}, {"id": "951863", "name": "\u9f8d\u8a6e", "address": "\u82d7\u6817\u7e23\u7af9\u5357\u93ae\u5c71\u4f73\u91cc\u9f8d\u5c71\u8def\u4e09\u6bb5305\u865f", "city": "\u82d7\u6817\u7e23", "town": "\u7af9\u5357\u93ae", "data": []}, {"id": "236685", "name": "\u9f8d\u9cf3", "address": "\u82d7\u6817\u7e23\u7af9\u5357\u93ae\u9f8d\u9cf3\u91cc\u9f8d\u6c5f\u885725\u865f", "city": "\u82d7\u6817\u7e23", "town": "\u7af9\u5357\u93ae", "data": []}, {"id": "199278", "name": "\u74b0\u7af9", "address": "\u82d7\u6817\u7e23\u7af9\u5357\u93ae\u74b0\u5e02\u8def\u4e00\u6bb516\u865f", "city": "\u82d7\u6817\u7e23", "town": "\u7af9\u5357\u93ae", "data": []}, {"id": "243328", "name": "\u85dd\u6587", "address": "\u82d7\u6817\u7e23\u7af9\u5357\u93ae\u65b0\u5357\u91cc\u516c\u5712\u8def118-6\u865f", "city": "\u82d7\u6817\u7e23", "town": "\u7af9\u5357\u93ae", "data": []}], "updatetime": 1762977114}