{"city": "\u53f0\u4e2d\u5e02", "town": "\u6771\u52e2\u5340", "zipcode": "423", "data": [{"id": "239710", "name": "\u6771\u5c55", "address": "\u53f0\u4e2d\u5e02\u6771\u52e2\u5340\u5357\u5e73\u91cc\u8c50\u52e2\u8def336\u865f", "city": "\u53f0\u4e2d\u5e02", "town": "\u6771\u52e2\u5340", "data": []}, {"id": "111865", "name": "\u6771\u6cf0", "address": "\u53f0\u4e2d\u5e02\u6771\u52e2\u5340\u6771\u862d\u8def41-5\u865f", "city": "\u53f0\u4e2d\u5e02", "town": "\u6771\u52e2\u5340", "data": []}, {"id": "142766", "name": "\u6771\u95dc", "address": "\u53f0\u4e2d\u5e02\u6771\u52e2\u5340\u6771\u95dc\u8def\u4e03\u6bb5191\u865f\u3001\u65b0\u76db\u88572\u865f1\u6a13", "city": "\u53f0\u4e2d\u5e02", "town": "\u6771\u52e2\u5340", "data": [{"name": "\u5e15\u6cf0\u5bb6-\u6930\u9999\u7da0\u5496\u54e9\u5ae9\u96de\u98ef", "qty": 1, "scate": "\u71f4\u98ef", "cate": "\u4fbf\u7576\u7ca5\u54c1"}]}, {"id": "208325", "name": "\u6771\u862d", "address": "\u53f0\u4e2d\u5e02\u6771\u52e2\u5340\u6771\u862d\u8def194\u865f", "city": "\u53f0\u4e2d\u5e02", "town": "\u6771\u52e2\u5340", "data": []}, {"id": "282600", "name": "\u6b23\u6771\u96f2", "address": "\u53f0\u4e2d\u5e02\u6771\u52e2\u5340\u7b2c\u4e94\u6a6b\u885728\u865f\u53ca\u4e09\u6c11\u8857165\u865f", "city": "\u53f0\u4e2d\u5e02", "town": "\u6771\u52e2\u5340", "data": [{"name": "\u2605\u6797\u8070\u660e-\u96de\u8089\u98ef\u98ef\u7cf0", "qty": 1, "scate": "\u4e09\u89d2\u98ef\u7cf0", "cate": "\u98ef\u7cf0\u624b\u5377"}]}, {"id": "249278", "name": "\u6b23\u6771\u52e2", "address": "\u53f0\u4e2d\u5e02\u6771\u52e2\u5340\u4e0a\u65b0\u91cc\u7b2c\u4e00\u6a6b\u8857153\u3001155\u865f1\u6a13\u548c\u4e09\u6c11\u88572\u865f1\u6a13", "city": "\u53f0\u4e2d\u5e02", "town": "\u6771\u52e2\u5340", "data": [{"name": "\u2605\u7099\u70e4\u9e7d\u8525\u71d2\u8089\u98ef\u7cf0", "qty": 1, "scate": "\u4e09\u89d2\u98ef\u7cf0", "cate": "\u98ef\u7cf0\u624b\u5377"}, {"name": "\u70e4\u96de\u71fb\u8178\u767d\u91ac\u7117\u98ef", "qty": 1, "scate": "\u7570\u570b\u6599\u7406/\u7117\u70e4", "cate": "\u4fbf\u7576\u7ca5\u54c1"}]}, {"id": "266435", "name": "\u6b23\u8056", "address": "\u53f0\u4e2d\u5e02\u6771\u52e2\u5340\u65b0\u76db\u8857290\u865f\u4e00\u6a13", "city": "\u53f0\u4e2d\u5e02", "town": "\u6771\u52e2\u5340", "data": []}, {"id": "231727", "name": "\u8018\u6668", "address": "\u53f0\u4e2d\u5e02\u6771\u52e2\u5340\u6771\u95dc\u8def\u516d\u6bb5432\u865f", "city": "\u53f0\u4e2d\u5e02", "town": "\u6771\u52e2\u5340", "data": [{"name": "\u6975\u9957-\u771f\u98fd\u9999\u8fa3\u9ebb\u91ac\u6dbc\u9eb5", "qty": 1, "scate": "\u6dbc\u9eb5", "cate": "\u9eb5\u98df"}, {"name": "\u7fa9\u5f0f\u8543\u8304\u8089\u91ac\u7fa9\u5927\u5229\u9eb5", "qty": 1, "scate": "\u7fa9\u5927\u5229\u9eb5", "cate": "\u9eb5\u98df"}]}, {"id": "155603", "name": "\u7cb5\u897f", "address": "\u53f0\u4e2d\u5e02\u6771\u52e2\u5340\u6771\u5751\u8def62\u865f1\u6a13", "city": "\u53f0\u4e2d\u5e02", "town": "\u6771\u52e2\u5340", "data": [{"name": "\u2605\u5317\u6d77\u9053\u79cb\u9bad\u9baa\u9b5a\u96d9\u624b\u5377", "qty": 1, "scate": "\u58fd\u53f8\u624b\u6372\u985e", "cate": "\u98ef\u7cf0\u624b\u5377"}, {"name": "\u2605\u9b5a\u5375\u9f8d\u8766\u98a8\u5473\u6c99\u62c9\u98ef\u7cf0", "qty": 1, "scate": "\u4e09\u89d2\u98ef\u7cf0", "cate": "\u98ef\u7cf0\u624b\u5377"}]}], "updatetime": 1762930563}