{"city": "\u53f0\u5357\u5e02", "town": "\u4e2d\u897f\u5340", "zipcode": "700", "data": [{"id": "242901", "name": "Fresh\u6e56\u7f8e", "address": "\u53f0\u5357\u5e02\u4e2d\u897f\u5340\u548c\u7def\u8def\u4e94\u6bb555\u865f", "city": "\u53f0\u5357\u5e02", "town": "\u4e2d\u897f\u5340", "data": []}, {"id": "885997", "name": "\u5343\u798f", "address": "\u53f0\u5357\u5e02\u4e2d\u897f\u5340\u5927\u6dbc\u91cc\u4e2d\u83ef\u897f\u8def\u4e8c\u6bb536\u865f", "city": "\u53f0\u5357\u5e02", "town": "\u4e2d\u897f\u5340", "data": []}, {"id": "139335", "name": "\u5927\u4e94", "address": "\u53f0\u5357\u5e02\u4e2d\u897f\u5340\u6cd5\u83ef\u91cc\u5927\u540c\u8def\u4e00\u6bb5218\u865f220\u865f", "city": "\u53f0\u5357\u5e02", "town": "\u4e2d\u897f\u5340", "data": []}, {"id": "253141", "name": "\u53cb\u611b", "address": "\u53f0\u5357\u5e02\u4e2d\u897f\u5340\u53cb\u611b\u8857197\u4e4b199\u865f", "city": "\u53f0\u5357\u5e02", "town": "\u4e2d\u897f\u5340", "data": []}, {"id": "252366", "name": "\u5929\u516c", "address": "\u53f0\u5357\u5e02\u4e2d\u897f\u5340\u5fe0\u7fa9\u8def\u4e8c\u6bb5109\u865f", "city": "\u53f0\u5357\u5e02", "town": "\u4e2d\u897f\u5340", "data": []}, {"id": "123156", "name": "\u6c34\u4ed9\u5bae", "address": "\u53f0\u5357\u5e02\u4e2d\u897f\u5340\u6c34\u4ed9\u91cc\u6c11\u6b0a\u8def\u4e09\u6bb587\u865f1\u6a13", "city": "\u53f0\u5357\u5e02", "town": "\u4e2d\u897f\u5340", "data": []}, {"id": "265362", "name": "\u53f0\u5357\u6c11\u65cf", "address": "\u53f0\u5357\u5e02\u4e2d\u897f\u5340\u516c\u6b63\u91cc\u6c11\u65cf\u8def\u4e8c\u6bb553\u865f", "city": "\u53f0\u5357\u5e02", "town": "\u4e2d\u897f\u5340", "data": []}, {"id": "256911", "name": "\u53f0\u5357\u661f\u947d", "address": "\u53f0\u5357\u5e02\u4e2d\u897f\u5340\u91d1\u83ef\u8def\u4e09\u6bb5218\u865f", "city": "\u53f0\u5357\u5e02", "town": "\u4e2d\u897f\u5340", "data": []}, {"id": "189019", "name": "\u6c38\u798f", "address": "\u53f0\u5357\u5e02\u4e2d\u897f\u5340\u6c38\u798f\u8def\u4e8c\u6bb565\u865f1\u6a13", "city": "\u53f0\u5357\u5e02", "town": "\u4e2d\u897f\u5340", "data": []}, {"id": "210074", "name": "\u5149\u8ce2", "address": "\u53f0\u5357\u5e02\u4e2d\u897f\u5340\u4e2d\u83ef\u897f\u8def\u4e8c\u6bb5600\u865f600-1\u865f1.2\u6a13", "city": "\u53f0\u5357\u5e02", "town": "\u4e2d\u897f\u5340", "data": []}, {"id": "165677", "name": "\u8d64\u5d01", "address": "\u53f0\u5357\u5e02\u4e2d\u897f\u5340\u6c11\u65cf\u8def\u4e8c\u6bb5331\u865f", "city": "\u53f0\u5357\u5e02", "town": "\u4e2d\u897f\u5340", "data": []}, {"id": "242473", "name": "\u4f70\u7d0d", "address": "\u53f0\u5357\u5e02\u4e2d\u897f\u5340\u6c11\u751f\u8def\u4e8c\u6bb5294\u865f1\u6a13", "city": "\u53f0\u5357\u5e02", "town": "\u4e2d\u897f\u5340", "data": []}, {"id": "130280", "name": "\u548c\u5584", "address": "\u53f0\u5357\u5e02\u4e2d\u897f\u5340\u85e5\u738b\u91cc\u6c11\u65cf\u8def\u4e09\u6bb56\u9130277\u865f1\u6a13", "city": "\u53f0\u5357\u5e02", "town": "\u4e2d\u897f\u5340", "data": []}, {"id": "230458", "name": "\u660e\u502b", "address": "\u53f0\u5357\u5e02\u4e2d\u897f\u5340\u91d1\u83ef\u8def\u4e09\u6bb588\u865f1.2\u6a13", "city": "\u53f0\u5357\u5e02", "town": "\u4e2d\u897f\u5340", "data": []}, {"id": "842060", "name": "\u6b66\u8056", "address": "\u53f0\u5357\u5e02\u4e2d\u897f\u5340\u6b66\u8056\u8def47\u865f49\u865f", "city": "\u53f0\u5357\u5e02", "town": "\u4e2d\u897f\u5340", "data": []}, {"id": "936484", "name": "\u6b66\u5fb7", "address": "\u53f0\u5357\u5e02\u4e2d\u897f\u5340\u9752\u5e74\u8def134\u865f", "city": "\u53f0\u5357\u5e02", "town": "\u4e2d\u897f\u5340", "data": []}, {"id": "136598", "name": "\u5357\u9580\u57ce", "address": "\u53f0\u5357\u5e02\u4e2d\u897f\u5340\u5357\u9580\u8def229\u865f1\u6a13", "city": "\u53f0\u5357\u5e02", "town": "\u4e2d\u897f\u5340", "data": []}, {"id": "239396", "name": "\u5357\u82f1", "address": "\u53f0\u5357\u5e02\u4e2d\u897f\u5340\u6c38\u798f\u8def\u4e00\u6bb530\u865f32\u865f1\u3001 2\u6a13", "city": "\u53f0\u5357\u5e02", "town": "\u4e2d\u897f\u5340", "data": []}, {"id": "129213", "name": "\u5357\u91ab", "address": "\u53f0\u5357\u5e02\u4e2d\u897f\u5340\u6c11\u65cf\u8def\u4e8c\u6bb576\u865f\u4e4b13", "city": "\u53f0\u5357\u5e02", "town": "\u4e2d\u897f\u5340", "data": []}, {"id": "252012", "name": "\u90e1\u738b", "address": "\u53f0\u5357\u5e02\u4e2d\u897f\u5340\u5e9c\u524d\u8def\u4e00\u6bb5144\u865f", "city": "\u53f0\u5357\u5e02", "town": "\u4e2d\u897f\u5340", "data": []}, {"id": "192783", "name": "\u552f\u52dd", "address": "\u53f0\u5357\u5e02\u4e2d\u897f\u5340\u6c11\u6b0a\u8def\u4e09\u6bb5150\u865f\u4e00\u6a13", "city": "\u53f0\u5357\u5e02", "town": "\u4e2d\u897f\u5340", "data": []}, {"id": "990905", "name": "\u5eb7\u6a02", "address": "\u53f0\u5357\u5e02\u4e2d\u897f\u5340\u5b89\u6d77\u91cc\u5eb7\u6a02\u8857223\u865f1\u6a13", "city": "\u53f0\u5357\u5e02", "town": "\u4e2d\u897f\u5340", "data": []}, {"id": "280305", "name": "\u9802\u7f8e", "address": "\u53f0\u5357\u5e02\u4e2d\u897f\u5340\u897f\u548c\u8def1\u865f3\u865f", "city": "\u53f0\u5357\u5e02", "town": "\u4e2d\u897f\u5340", "data": []}, {"id": "159133", "name": "\u6676\u8d8a", "address": "\u53f0\u5357\u5e02\u4e2d\u897f\u5340\u897f\u9580\u8def\u4e00\u6bb5658\u865fB2", "city": "\u53f0\u5357\u5e02", "town": "\u4e2d\u897f\u5340", "data": []}, {"id": "262293", "name": "\u6e56\u83ef", "address": "\u53f0\u5357\u5e02\u4e2d\u897f\u5340\u897f\u6e56\u88573\u865f", "city": "\u53f0\u5357\u5e02", "town": "\u4e2d\u897f\u5340", "data": []}, {"id": "251743", "name": "\u958b\u5c71", "address": "\u53f0\u5357\u5e02\u4e2d\u897f\u5340\u958b\u5c71\u8def245\u865f1\u6a13", "city": "\u53f0\u5357\u5e02", "town": "\u4e2d\u897f\u5340", "data": []}, {"id": "277701", "name": "\u96c6\u798f", "address": "\u53f0\u5357\u5e02\u4e2d\u897f\u5340\u91d1\u83ef\u8def\u56db\u6bb5194\u865f\u8207\u4fe1\u7fa9\u885760\u5df76\u865f", "city": "\u53f0\u5357\u5e02", "town": "\u4e2d\u897f\u5340", "data": []}, {"id": "217499", "name": "\u65b0\u6c38\u5065", "address": "\u53f0\u5357\u5e02\u4e2d\u897f\u5340\u5065\u5eb7\u8def\u4e00\u6bb5346\u865f", "city": "\u53f0\u5357\u5e02", "town": "\u4e2d\u897f\u5340", "data": []}, {"id": "254546", "name": "\u65b0\u6c38\u83ef", "address": "\u53f0\u5357\u5e02\u4e2d\u897f\u5340\u6c38\u83ef\u8def\u4e00\u6bb5248\u865f1\u6a13", "city": "\u53f0\u5357\u5e02", "town": "\u4e2d\u897f\u5340", "data": []}, {"id": "234601", "name": "\u65b0\u5149\u7f8e", "address": "\u53f0\u5357\u5e02\u4e2d\u897f\u5340\u4e2d\u5c71\u8def162\u865fB2\u6a13", "city": "\u53f0\u5357\u5e02", "town": "\u4e2d\u897f\u5340", "data": []}, {"id": "973014", "name": "\u65b0\u904b\u6cb3", "address": "\u53f0\u5357\u5e02\u4e2d\u897f\u5340\u5e9c\u524d\u8def\u4e8c\u6bb5239\u865f1\u6a13", "city": "\u53f0\u5357\u5e02", "town": "\u4e2d\u897f\u5340", "data": []}, {"id": "167134", "name": "\u7d9c\u5408", "address": "\u53f0\u5357\u5e02\u4e2d\u897f\u5340\u6c34\u4ed9\u91cc\u6c11\u751f\u8def\u4e8c\u6bb526\u865f28\u865f1\u6a13", "city": "\u53f0\u5357\u5e02", "town": "\u4e2d\u897f\u5340", "data": []}, {"id": "278807", "name": "\u93ae\u5c71", "address": "\u53f0\u5357\u5e02\u4e2d\u897f\u5340\u897f\u6e56\u91cc\u6e56\u7f8e\u885710\u865f", "city": "\u53f0\u5357\u5e02", "town": "\u4e2d\u897f\u5340", "data": []}, {"id": "252252", "name": "\u9ad4\u80b2", "address": "\u53f0\u5357\u5e02\u4e2d\u897f\u5340\u5065\u5eb7\u8def\u4e00\u6bb5166\u865f", "city": "\u53f0\u5357\u5e02", "town": "\u4e2d\u897f\u5340", "data": []}], "updatetime": 1762902871}