{"city": "\u82b1\u84ee\u7e23", "town": "\u5353\u6eaa\u9109", "zipcode": "982", "data": [{"id": "231185", "name": "\u5353\u6eaa", "address": "\u82b1\u84ee\u7e23\u5353\u6eaa\u9109\u5353\u6eaa\u6751\u4e2d\u6b6357-6\u865f", "city": "\u82b1\u84ee\u7e23", "town": "\u5353\u6eaa\u9109", "data": [{"name": "\u7d71\u4e00\u9eb5\u5305\u5361\u58eb\u9054\u9eb5\u5305.", "qty": 1, "scate": "\u9eb5\u5305", "cate": "\u9eb5\u5305\u86cb\u7cd5"}, {"name": "\u9999\u5e25-\u828b\u6ce5\u8089\u9b06\u9eb5\u5305", "qty": 1, "scate": "\u9eb5\u5305", "cate": "\u9eb5\u5305\u86cb\u7cd5"}, {"name": "\u7d71\u4e00\u9eb5\u5305\u7cd6\u871c\u9999\u7d05\u8c46\u9eb5\u5305", "qty": 1, "scate": "\u9eb5\u5305", "cate": "\u9eb5\u5305\u86cb\u7cd5"}, {"name": "\u7d71\u4e00\u9eb5\u5305\u5976\u9165\u9eb5\u5305", "qty": 2, "scate": "\u9eb5\u5305", "cate": "\u9eb5\u5305\u86cb\u7cd5"}, {"name": "\u8349\u8393\u679c\u6ce5\u9eb5\u5305", "qty": 2, "scate": "\u9eb5\u5305", "cate": "\u9eb5\u5305\u86cb\u7cd5"}, {"name": "\u7d71\u4e00\u9eb5\u5305\u8349\u8393\u593e\u5fc3\u9eb5\u5305", "qty": 2, "scate": "\u9eb5\u5305", "cate": "\u9eb5\u5305\u86cb\u7cd5"}, {"name": "(\u540a)\u5341\u4e09\u9999\u70e4\u96de\u7fc5", "qty": 1, "scate": "\u914d\u83dc", "cate": "\u914d\u83dc\u6e6f\u54c1"}, {"name": "(\u540a)\u5fa1\u6599\u5c0f\u9928\u7f8e\u5f0f\u9999\u8fa3\u96de\u4e01", "qty": 1, "scate": "\u914d\u83dc", "cate": "\u914d\u83dc\u6e6f\u54c1"}, {"name": "(\u540a)21Plus\u849c\u9999\u9e7d\u9165\u96de", "qty": 3, "scate": "\u914d\u83dc", "cate": "\u914d\u83dc\u6e6f\u54c1"}, {"name": "LaDears\u84ee\u82b1\u7126\u7cd6\u8106\u9905\u5df4\u65af\u514b", "qty": 1, "scate": "\u86cb\u7cd5", "cate": "\u751c\u9ede"}, {"name": "LADEARS \u828b\u6ce5\u751f\u4e73\u6372", "qty": 2, "scate": "\u86cb\u7cd5", "cate": "\u751c\u9ede"}, {"name": "QQ\u5361\u58eb\u9054\u534a\u6708\u71d2", "qty": 2, "scate": "\u86cb\u7cd5", "cate": "\u751c\u9ede"}, {"name": "\u82b1\u751f\u7194\u5ca9\u8fa3\u96de\u817f\u5821", "qty": 1, "scate": "\u6f22\u5821", "cate": "\u4e09\u660e\u6cbb\u5821\u985e"}, {"name": "\u8349\u8393\u4e73\u916a\u4e09\u660e\u6cbb", "qty": 1, "scate": "\u888b\u88dd\u4e09\u660e\u6cbb", "cate": "\u4e09\u660e\u6cbb\u5821\u985e"}, {"name": "(3XL)\u65e5\u5f0f\u96de\u86cb\u6c99\u62c9\u4e09\u660e\u6cbb", "qty": 1, "scate": "\u888b\u88dd\u4e09\u660e\u6cbb", "cate": "\u4e09\u660e\u6cbb\u5821\u985e"}, {"name": "\u8766\u6392\u7e3d\u532f\u4e09\u660e\u6cbb", "qty": 1, "scate": "\u888b\u88dd\u4e09\u660e\u6cbb", "cate": "\u4e09\u660e\u6cbb\u5821\u985e"}, {"name": "\u6e8f\u5fc3\u86cb\u7d10\u5967\u826f\u98a8\u5473\u70e4\u96de\u4e09\u660e\u6cbb", "qty": 2, "scate": "\u888b\u88dd\u4e09\u660e\u6cbb", "cate": "\u4e09\u660e\u6cbb\u5821\u985e"}, {"name": "\u8d77\u53f8\u56db\u5408\u594f\u4e09\u660e\u6cbb", "qty": 3, "scate": "\u888b\u88dd\u4e09\u660e\u6cbb", "cate": "\u4e09\u660e\u6cbb\u5821\u985e"}, {"name": "\u5e15\u6cf0\u5bb6-\u6930\u9999\u7da0\u5496\u54e9\u5ae9\u96de\u98ef", "qty": 1, "scate": "\u71f4\u98ef", "cate": "\u4fbf\u7576\u7ca5\u54c1"}, {"name": "\u6975\u9957-\u9ebb\u6cb9\u8c6c\u8089\u98ef", "qty": 1, "scate": "\u71f4\u98ef", "cate": "\u4fbf\u7576\u7ca5\u54c1"}, {"name": "\u5409\u58eb\u96de\u8089\u86cb\u5821", "qty": 1, "scate": "\u746a\u82ac\u5821", "cate": "\u4e09\u660e\u6cbb\u5821\u985e"}, {"name": "\u5409\u58eb\u8c6c\u8089\u5821\u52a0\u86cb", "qty": 2, "scate": "\u746a\u82ac\u5821", "cate": "\u4e09\u660e\u6cbb\u5821\u985e"}, {"name": "\u8525\u9e7d\u96de\u817f\u6eab\u6642\u852c", "qty": 1, "scate": "\u4e3b\u98df\u578b\u6c99\u62c9", "cate": "\u6c99\u62c9"}, {"name": "\u85af\u6ce5\u9bae\u852c\u86cb\u6c99\u62c9", "qty": 2, "scate": "\u4e3b\u98df\u578b\u6c99\u62c9", "cate": "\u6c99\u62c9"}, {"name": "\u97d3\u5f0f\u70b8\u96de\u8d77\u53f8\u4e3c", "qty": 1, "scate": "\u7570\u570b\u6599\u7406/\u7117\u70e4", "cate": "\u4fbf\u7576\u7ca5\u54c1"}, {"name": "\u6d93\u8c46\u8150\u97d3\u5f0f\u96dc\u83dc\u51ac\u7c89", "qty": 1, "scate": "\u914d\u83dc\u578b\u6c99\u62c9", "cate": "\u6c99\u62c9"}, {"name": "\u7fa9\u5f0f\u9752\u91ac\u4f50\u6642\u852c", "qty": 1, "scate": "\u914d\u83dc\u578b\u6c99\u62c9", "cate": "\u6c99\u62c9"}, {"name": "\u97d3\u5f0f\u9ebb\u85e5\u6e8f\u5fc3\u86cb", "qty": 2, "scate": "\u914d\u83dc\u578b\u6c99\u62c9", "cate": "\u6c99\u62c9"}, {"name": "\u6d77\u9bae\u7117\u70e4\u7c73\u578b\u9eb5", "qty": 1, "scate": "\u7fa9\u5927\u5229\u9eb5", "cate": "\u9eb5\u98df"}, {"name": "\u97d3\u5f0f\u70b8\u96de\u539a\u571f\u53f8", "qty": 1, "scate": "\u76d2\u88dd\u4e09\u660e\u6cbb", "cate": "\u4e09\u660e\u6cbb\u5821\u985e"}, {"name": "\u7194\u5ca9\u8d77\u53f8\u71fb\u57f9\u6839\u539a\u571f\u53f8", "qty": 3, "scate": "\u76d2\u88dd\u4e09\u660e\u6cbb", "cate": "\u4e09\u660e\u6cbb\u5821\u985e"}, {"name": "\u7ca5\u5929\u5b50-\u5ee3\u5f0f\u76ae\u86cb\u7626\u8089\u7172\u7ca5", "qty": 1, "scate": "\u7ca5\u54c1", "cate": "\u4fbf\u7576\u7ca5\u54c1"}, {"name": "(\u852c)\u5c0f\u5c0f\u6a39\u98df\u85dc\u9ea5\u5f69\u852c\u9910\u76d2", "qty": 1, "scate": "\u852c\u98df\u4fbf\u7576", "cate": "\u4fbf\u7576\u7ca5\u54c1"}, {"name": "\u6602\u8212\u5df4\u9ece\u699b\u679c\u5de7\u514b\u529b\u6ce1\u8299", "qty": 2, "scate": "\u6ce1\u8299", "cate": "\u751c\u9ede"}, {"name": "\u97d3\u5f0f\u70e4\u725b\u8089\u591a\u5f69\u98ef\u5377", "qty": 2, "scate": "4\u2103\u52a0\u71b1\u98ef\u7cf0", "cate": "\u98ef\u7cf0\u624b\u5377"}, {"name": "\u7206\u6f3f\u71fb\u8178\u8d77\u53f8\u98ef\u5377", "qty": 3, "scate": "4\u2103\u52a0\u71b1\u98ef\u7cf0", "cate": "\u98ef\u7cf0\u624b\u5377"}, {"name": "\u8d77\u53f8\u56db\u91cd\u594f\u71b1\u72d7\u5821", "qty": 2, "scate": "\u9577\u5821", "cate": "\u4e09\u660e\u6cbb\u5821\u985e"}, {"name": "\u6975\u9957-\u9752\u82b1\u6912\u96de\u817f\u6392\u6ce2\u6d6a\u9eb5", "qty": 2, "scate": "\u7092\u9eb5", "cate": "\u9eb5\u98df"}]}], "updatetime": 1763039026}